{"version":3,"commands":{},"prefs":{"privacy.containers":{"initialValue":{},"precedenceList":[{"id":"firefox@tampermonkey.net","installDate":1780741205650,"value":"firefox@tampermonkey.net","enabled":true}]},"contextMenuShowEvent":{"initialValue":{},"precedenceList":[{"id":"{506e023c-7f2b-40a3-8066-bc5deb40aebe}","installDate":1780742675751,"value":"mouseup","enabled":true}]},"websites.hyperlinkAuditingEnabled":{"initialValue":{},"precedenceList":[{"id":"uBlock0@raymondhill.net","installDate":1780764379313,"value":false,"enabled":true}]},"network.networkPredictionEnabled":{"initialValue":{},"precedenceList":[{"id":"uBlock0@raymondhill.net","installDate":1780764379313,"value":false,"enabled":true}]}},"tabHideNotification":{},"homepageNotification":{},"default_search":{},"newTabNotification":{},"url_overrides":{}}